log/__init__.py
log/api/__init__.py
log/api/logger.py
log/config/color_logger_config.py
log/config/logging.yaml
log/core/_init_.py
log/core/formatter.py
log/core/loader.py
log/core/manager.py
log/core/proxy.py
lili_logger-1.0.0.dist-info/METADATA
lili_logger-1.0.0.dist-info/WHEEL
lili_logger-1.0.0.dist-info/top_level.txt
lili_logger-1.0.0.dist-info/RECORD
