Metadata-Version: 2.4
Name: lili-logger
Version: 1.0.0
Summary: 一个帅气专业的彩色日志系统
Author: Lili
Author-email: Lili <tkin.l@qq.com>
License: MIT
Project-URL: Homepage, https://github.com/tonkin/lili-logger
Project-URL: Bug Reports, https://github.com/tonkin/lili-logger/issues
Project-URL: Source, https://github.com/tonkin/lili-logger
Keywords: logging,color,logger,lili,colored-logs
Classifier: Development Status :: 4 - Beta
Classifier: Intended Audience :: Developers
Classifier: License :: OSI Approved :: MIT License
Classifier: Operating System :: OS Independent
Classifier: Programming Language :: Python :: 3
Classifier: Programming Language :: Python :: 3.7
Classifier: Programming Language :: Python :: 3.8
Classifier: Programming Language :: Python :: 3.9
Classifier: Programming Language :: Python :: 3.10
Classifier: Programming Language :: Python :: 3.11
Classifier: Topic :: System :: Logging
Classifier: Topic :: Software Development :: Libraries :: Python Modules
Requires-Python: >=3.7
Requires-Dist: PyYAML>=5.4
Requires-Dist: psutil>=5.8; platform_system != "Windows"
Provides-Extra: dev
Requires-Dist: pytest>=6.0; extra == "dev"
Requires-Dist: black>=21.0; extra == "dev"
Requires-Dist: flake8>=3.9; extra == "dev"
Requires-Dist: mypy>=0.910; extra == "dev"
Provides-Extra: test
Requires-Dist: pytest>=6.0; extra == "test"
Requires-Dist: pytest-cov>=2.0; extra == "test"
Provides-Extra: docs
Requires-Dist: sphinx>=4.0; extra == "docs"
Requires-Dist: sphinx-rtd-theme>=1.0; extra == "docs"
Provides-Extra: full
Requires-Dist: psutil>=5.8; extra == "full"
Dynamic: author
Dynamic: requires-python
